setup.cfg
setup.py
sharepa/__init__.py
sharepa/analysis.py
sharepa/helpers.py
sharepa/search.py
sharepa.egg-info/PKG-INFO
sharepa.egg-info/SOURCES.txt
sharepa.egg-info/dependency_links.txt
sharepa.egg-info/requires.txt
sharepa.egg-info/top_level.txt