Metadata-Version: 1.1
Name: sharepa
Version: 0.2.1
Summary: A library for browsing and analyzing SHARE data
Home-page: https://github.com/fabianvf/sharepa
Author: Fabian von Feilitzsch
Author-email: fabian@cos.io
License: UNKNOWN
Download-URL: https://github.com/fabianvf/sharepa/tarball/0.2.1
Platform: UNKNOWN
